televoice/__init__.py
televoice/bot.py
televoice/main.py
televoice/py.typed
televoice/utils.py
televoice/apis/__init__.py
televoice/apis/exchange.py
televoice/apis/whisper.py
televoice-0.1.0.dist-info/METADATA
televoice-0.1.0.dist-info/WHEEL
televoice-0.1.0.dist-info/entry_points.txt
televoice-0.1.0.dist-info/top_level.txt
televoice-0.1.0.dist-info/RECORD
