Metadata-Version: 2.1
Name: televoice
Version: 0.1.0
Maintainer: Fernando Perez-Garcia
Maintainer-email: fepegar@gmail.com
License: MIT
Project-URL: Source, https://github.com/fepegar/telegram-gpt-bot
Platform: OS Independent
Classifier: Development Status :: 4 - Beta
Classifier: Environment :: Console
Classifier: Intended Audience :: Science/Research
Classifier: Natural Language :: English
Classifier: Operating System :: OS Independent
Classifier: Programming Language :: Python
Classifier: Programming Language :: Python :: 3
Classifier: Programming Language :: Python :: 3 :: Only
Classifier: Programming Language :: Python :: 3.7
Classifier: Programming Language :: Python :: 3.8
Classifier: Programming Language :: Python :: 3.9
Classifier: Programming Language :: Python :: 3.10
Classifier: Programming Language :: Python :: 3.11
Classifier: Programming Language :: Python :: Implementation :: CPython
Classifier: Topic :: Scientific/Engineering
Classifier: Topic :: Scientific/Engineering :: Artificial Intelligence
Classifier: Typing :: Typed
Requires-Python: >=3.7
Requires-Dist: CurrencyConverter
Requires-Dist: openai
Requires-Dist: pydub
Requires-Dist: python-telegram-bot
Requires-Dist: rich
